openvino_nvidia/__init__.py
openvino_nvidia/lib/libopenvino_nvidia_gpu_plugin.so
openvino_nvidia-2025.3.1.dist-info/METADATA
openvino_nvidia-2025.3.1.dist-info/WHEEL
openvino_nvidia-2025.3.1.dist-info/top_level.txt
openvino_nvidia-2025.3.1.dist-info/RECORD
