Metadata-Version: 2.1
Name: openvino-nvidia
Version: 2025.3.1
Summary: NVIDIA Plugin for OpenVINO Inference Engine Python* API
Home-page: https://docs.openvinotoolkit.org/latest/index.html
Download-URL: https://github.com/openvinotoolkit/openvino/tags
Author: Intel Corporation
Author-email: openvino_pushbot@intel.com
License: OSI Approved :: Apache Software License
Dynamic: author
Dynamic: author-email
Dynamic: description
Dynamic: description-content-type
Dynamic: download-url
Dynamic: home-page
Dynamic: license
Dynamic: summary
